{
  "color": "red",
  "cols": 5,
  "rows": 2,
  "sheetW": 600,
  "sheetH": 400,
  "rects": [
    [
      44,
      59,
      75,
      114
    ],
    [
      139,
      58,
      82,
      115
    ],
    [
      240,
      52,
      86,
      121
    ],
    [
      340,
      53,
      94,
      117
    ],
    [
      470,
      54,
      93,
      119
    ],
    [
      28,
      249,
      92,
      120
    ],
    [
      128,
      246,
      100,
      122
    ],
    [
      234,
      246,
      100,
      125
    ],
    [
      340,
      243,
      101,
      125
    ],
    [
      474,
      243,
      103,
      122
    ]
  ]
}